panza/__init__.py
panza/cache.py
panza/conftest.py
panza/limit_concurrency.py
panza/s3_backend.py
panza/sqlite_backend.py
panza/test_cache.py
panza/test_s3_cache.py
panza-0.2.2.dist-info/licenses/LICENSE
panza-0.2.2.dist-info/METADATA
panza-0.2.2.dist-info/WHEEL
panza-0.2.2.dist-info/top_level.txt
panza-0.2.2.dist-info/RECORD
