Metadata-Version: 2.4
Name: panza
Version: 0.2.2
Summary: Experimental sqlite caching and concurrency limiting
Requires-Python: >=3.10
License-File: LICENSE
Provides-Extra: s3
Requires-Dist: aioboto3>=13.4.0; extra == "s3"
Dynamic: license-file
